redis_enterprise/__init__.py
redis_enterprise/redis_enterprise.cpython-312-darwin.so
redis_enterprise-0.1.0.dist-info/METADATA
redis_enterprise-0.1.0.dist-info/WHEEL
redis_enterprise-0.1.0.dist-info/RECORD
