Metadata-Version: 2.4
Name: redis-enterprise
Version: 0.1.0
Classifier: Development Status :: 4 - Beta
Classifier: Intended Audience :: Developers
Classifier: License :: OSI Approved :: MIT License
Classifier: License :: OSI Approved :: Apache Software License
Classifier: Programming Language :: Python :: 3
Classifier: Programming Language :: Python :: 3.9
Classifier: Programming Language :: Python :: 3.10
Classifier: Programming Language :: Python :: 3.11
Classifier: Programming Language :: Python :: 3.12
Classifier: Programming Language :: Python :: 3.13
Classifier: Programming Language :: Rust
Classifier: Topic :: Database
Classifier: Typing :: Typed
Requires-Dist: pytest>=7.0 ; extra == 'dev'
Requires-Dist: pytest-asyncio>=0.21 ; extra == 'dev'
Provides-Extra: dev
Summary: Python bindings for Redis Enterprise REST API client
Keywords: redis,enterprise,api,rest,client
Home-Page: https://github.com/redis-developer/redis-enterprise-rs
Author-email: Josh Rotenberg <joshrotenberg@gmail.com>
License: MIT OR Apache-2.0
Requires-Python: >=3.9
Project-URL: Documentation, https://docs.rs/redis-enterprise
Project-URL: Homepage, https://github.com/redis-developer/redis-enterprise-rs
Project-URL: Repository, https://github.com/redis-developer/redis-enterprise-rs
